aioesphomeapi/__init__.py
aioesphomeapi/api_options_pb2.py
aioesphomeapi/api_pb2.py
aioesphomeapi/ble_defs.py
aioesphomeapi/client.py
aioesphomeapi/client_base.cpython-314-aarch64-linux-musl.so
aioesphomeapi/client_base.py
aioesphomeapi/connection.cpython-314-aarch64-linux-musl.so
aioesphomeapi/connection.py
aioesphomeapi/core.py
aioesphomeapi/discover.py
aioesphomeapi/host_resolver.py
aioesphomeapi/log_parser.py
aioesphomeapi/log_reader.py
aioesphomeapi/log_runner.py
aioesphomeapi/model.py
aioesphomeapi/model_conversions.py
aioesphomeapi/object_id.py
aioesphomeapi/py.typed
aioesphomeapi/reconnect_logic.py
aioesphomeapi/singleton.py
aioesphomeapi/timezone.py
aioesphomeapi/util.py
aioesphomeapi/zeroconf.py
aioesphomeapi/_frame_helper/__init__.py
aioesphomeapi/_frame_helper/base.cpython-314-aarch64-linux-musl.so
aioesphomeapi/_frame_helper/base.py
aioesphomeapi/_frame_helper/noise.cpython-314-aarch64-linux-musl.so
aioesphomeapi/_frame_helper/noise.py
aioesphomeapi/_frame_helper/noise_encryption.cpython-314-aarch64-linux-musl.so
aioesphomeapi/_frame_helper/noise_encryption.py
aioesphomeapi/_frame_helper/pack.cpython-314-aarch64-linux-musl.so
aioesphomeapi/_frame_helper/packets.cpython-314-aarch64-linux-musl.so
aioesphomeapi/_frame_helper/packets.py
aioesphomeapi/_frame_helper/plain_text.cpython-314-aarch64-linux-musl.so
aioesphomeapi/_frame_helper/plain_text.py
aioesphomeapi-43.14.0.dist-info/METADATA
aioesphomeapi-43.14.0.dist-info/WHEEL
aioesphomeapi-43.14.0.dist-info/entry_points.txt
aioesphomeapi-43.14.0.dist-info/top_level.txt
aioesphomeapi-43.14.0.dist-info/RECORD
aioesphomeapi-43.14.0.dist-info/licenses/LICENSE
