Metadata-Version: 2.4
Name: aioesphomeapi
Version: 43.14.0
Summary: Python API for interacting with ESPHome devices.
Home-page: https://esphome.io/
Download-URL: https://github.com/esphome/aioesphomeapi/archive/43.14.0.zip
Author: Otto Winter
Author-email: esphome@nabucasa.com
License: MIT
Requires-Python: >=3.11
License-File: LICENSE
Requires-Dist: aiohappyeyeballs>=2.3.0
Requires-Dist: async-interrupt>=1.2.0
Requires-Dist: protobuf<8,>=6
Requires-Dist: tzlocal<6,>=5.0
Requires-Dist: zeroconf<2.0,>=0.143.0
Requires-Dist: chacha20poly1305-reuseable>=0.13.2
Requires-Dist: cryptography>=43.0.0
Requires-Dist: noiseprotocol<1.0,>=0.3.1
Dynamic: author
Dynamic: author-email
Dynamic: description
Dynamic: download-url
Dynamic: home-page
Dynamic: license
Dynamic: license-file
Dynamic: requires-dist
Dynamic: requires-python
Dynamic: summary
